gms/GMSModule.py
gms/__init__.py
gms-0.4.0.dist-info/LICENSE
gms-0.4.0.dist-info/METADATA
gms-0.4.0.dist-info/WHEEL
gms-0.4.0.dist-info/top_level.txt
gms-0.4.0.dist-info/RECORD
