Metadata-Version: 2.1
Name: gms
Version: 0.4.0
Summary: General Model Selection Module
Home-page: https://github.com/plugg1N/gms-module
Author: plugg1N (Nikita Zhamkov Dmitrievich)
Author-email: nikitazhamkov@gmail.com
Project-URL: Documentation, https://github.com/plugg1N/gms-module/blob/main/README.md
Project-URL: Project_github, https://github.com/plugg1N/gms-module
Keywords: python machine-learning ml models ai
Classifier: Programming Language :: Python :: 3.10
Classifier: License :: OSI Approved :: MIT License
Classifier: Operating System :: OS Independent
Requires-Python: >=3.7
License-File: LICENSE
Requires-Dist: requests (>=2.25.1)
